{
  "${ModID}:TodoItem": {
    "NAME": "Todo Item",
    "FLAVOR": "TODO: make this a sweet relic.",
    "DESCRIPTIONS": [
      "Has no effect."
    ]
  },
  "${ModID}:Antibodies": {
    "NAME": "Antibodies",
    "FLAVOR": "TODO: make this a sweet relic.",
    "DESCRIPTIONS": [
      "At the end of combat, gain #b"," Max HP"
    ]
  },
  "${ModID}:GoldenShovel": {
    "NAME": "Golden Shovel",
    "FLAVOR": "TODO: make this a sweet relic.",
    "DESCRIPTIONS": [
      "At the end of combat, gain #b"," Golds."
    ]
  }
}